{
  "errors": [],
  "warnings": [],
  "hash": "222953f91e836922b1a9",
  "publicPath": "",
  "outputPath": "C:\\webb\\gc2-frontity\\build\\static",
  "assetsByChunkName": {
    "gc2-frontity": [
      "gc2-frontity.module.js",
      "gc2-frontity.b05869873203ec89c7d5.hot-update.js"
    ]
  },
  "assets": [
    {
      "name": "b05869873203ec89c7d5.hot-update.json",
      "size": 54,
      "chunks": [],
      "chunkNames": [],
      "info": {
        "hotModuleReplacement": true,
        "immutable": true
      },
      "emitted": false
    },
    {
      "name": "fonts/Roboto-Bold.ttf",
      "size": 167336,
      "chunks": [],
      "chunkNames": [],
      "info": {
        "sourceFilename": "packages/grafikcentralen/src/components/fonts/Roboto-Bold.ttf"
      },
      "emitted": false
    },
    {
      "name": "fonts/Roboto-Medium.ttf",
      "size": 168644,
      "chunks": [],
      "chunkNames": [],
      "info": {
        "sourceFilename": "packages/grafikcentralen/src/components/fonts/Roboto-Medium.ttf"
      },
      "emitted": false
    },
    {
      "name": "gc2-frontity.b05869873203ec89c7d5.hot-update.js",
      "size": 109407,
      "chunks": [
        "gc2-frontity"
      ],
      "chunkNames": [
        "gc2-frontity"
      ],
      "info": {
        "hotModuleReplacement": true,
        "immutable": true
      },
      "emitted": false
    },
    {
      "name": "gc2-frontity.module.js",
      "size": 7254460,
      "chunks": [
        "gc2-frontity"
      ],
      "chunkNames": [
        "gc2-frontity"
      ],
      "info": {},
      "emitted": false
    }
  ],
  "filteredAssets": 0,
  "namedChunkGroups": {
    "gc2-frontity": {
      "chunks": [
        "gc2-frontity"
      ],
      "assets": [
        "gc2-frontity.module.js",
        "gc2-frontity.b05869873203ec89c7d5.hot-update.js"
      ],
      "children": {},
      "childAssets": {}
    }
  },
  "generator": "loadable-components",
  "chunks": [
    {
      "id": "gc2-frontity",
      "files": [
        "gc2-frontity.module.js",
        "gc2-frontity.b05869873203ec89c7d5.hot-update.js"
      ]
    }
  ]
}